LICENSE
README.md
setup.py
chainlit_client/__init__.py
chainlit_client/api.py
chainlit_client/client.py
chainlit_client/context.py
chainlit_client/event_processor.py
chainlit_client/message.py
chainlit_client/my_types.py
chainlit_client/py.typed
chainlit_client/requirements.py
chainlit_client/step.py
chainlit_client/thread.py
chainlit_client/version.py
chainlit_client/wrappers.py
chainlit_client.egg-info/PKG-INFO
chainlit_client.egg-info/SOURCES.txt
chainlit_client.egg-info/dependency_links.txt
chainlit_client.egg-info/requires.txt
chainlit_client.egg-info/top_level.txt
chainlit_client/callback/__init__.py
chainlit_client/callback/langchain_callback.py
chainlit_client/instrumentation/__init__.py
chainlit_client/instrumentation/openai.py
tests/__init__.py