Metadata-Version: 1.0
Name: chainlit-client
Version: 0.1.0rc10
Summary: An SDK for observability in Python applications
Home-page: UNKNOWN
Author: UNKNOWN
Author-email: UNKNOWN
License: UNKNOWN
Platform: UNKNOWN
